thinknet_airflow_dag_artifact/__init__.py
thinknet_airflow_dag_artifact/error_data.py
thinknet_airflow_dag_artifact/spark_utilities.py
thinknet_airflow_dag_artifact/xcom_utilities.py
thinknet_airflow_dag_artifact-1.0.0a1.dist-info/METADATA
thinknet_airflow_dag_artifact-1.0.0a1.dist-info/WHEEL
thinknet_airflow_dag_artifact-1.0.0a1.dist-info/top_level.txt
thinknet_airflow_dag_artifact-1.0.0a1.dist-info/RECORD
