Metadata-Version: 2.1
Name: thinknet-airflow-dag-artifact
Version: 1.0.0a1
Summary: Airflow artifact manager for data-eng@thinknet
Author-email: TN-DE Team <thinknet_dataengineer@thinknet.co.th>
Project-URL: Homepage, https://gitlab.thinknet.co.th/data-eng/library/airflow-dag-artifact
Classifier: Intended Audience :: Developers
Classifier: Programming Language :: Python :: 3.8
Classifier: Programming Language :: Python :: 3.9
Classifier: Programming Language :: Python :: 3.10
Classifier: Programming Language :: Python :: 3.11
Classifier: Programming Language :: Python :: 3.12
Classifier: Development Status :: 3 - Alpha
Classifier: Topic :: Software Development :: Libraries
Requires-Python: >=3.8
Requires-Dist: botocore >=1.35
Requires-Dist: pyspark >=3.5
Requires-Dist: thinknet-application-specific-exception >=1.0.0rc0
Requires-Dist: thinknet-variable-validator >=1.0.0b4
Provides-Extra: dev
Requires-Dist: pytest ; extra == 'dev'
